{
  "anchor_id": "wt-8.2-enhanced-sidebar-v3.1-complete",
  "project": "Wombat Track",
  "phase": "WT-8.2",
  "status": "Complete",
  "commit": "43a48c4",
  "branch": "main",
  "description": "Enhanced Sidebar v3.1 fully merged and SDLC Phase 3 QA complete. Governance, MemoryPlugin, and DriveMemory artifacts finalized.",
  "timestamp": "2025-08-03T18:48:00+10:00",
  "uat_results": {
    "scenarios_completed": 5,
    "governance_events": 14,
    "console_messages": 338,
    "screenshots_captured": true,
    "artifacts_archived": true,
    "sdlc_compliance": "ACHIEVED"
  },
  "features_merged": [
    "Enhanced three-tier sidebar navigation",
    "Operating Sub-Apps section with live status",
    "Project Work Surfaces (Plan→Execute→Document→Govern)",
    "System Surfaces (Admin/Integration/SPQR)",
    "Governance logging with MemoryPlugin integration",
    "Mock data fallback mechanisms",
    "Error boundaries for stability",
    "Comprehensive UAT test suite"
  ]
}