{
  "phase": "OF-9.2.4.1",
  "summary": "Azure App Insights Components Created Successfully",
  "timestamp": "2025-08-08T11:07:00Z",
  "components": {
    "backend": {
      "name": "WT-Backend-Insights",
      "appId": "6b7f280c-cf44-4fda-9985-215c272b3ad9",
      "instrumentationKey": "e772a6e3-86c9-48f6-a220-e4fff3d32f25",
      "connectionString": "InstrumentationKey=e772a6e3-86c9-48f6-a220-e4fff3d32f25;IngestionEndpoint=https://australiaeast-1.in.applicationinsights.azure.com/;LiveEndpoint=https://australiaeast.livediagnostics.monitor.azure.com/;ApplicationId=6b7f280c-cf44-4fda-9985-215c272b3ad9",
      "resourceGroup": "of-8-6-cloud-rg",
      "location": "australiaeast",
      "provisioningState": "Succeeded"
    },
    "frontend": {
      "name": "WT-Frontend-Insights",
      "appId": "8404bd9a-2eda-40de-a2d5-11015a59d55f",
      "instrumentationKey": "919391a9-ea0c-4aac-97da-804672a75c19",
      "connectionString": "InstrumentationKey=919391a9-ea0c-4aac-97da-804672a75c19;IngestionEndpoint=https://australiaeast-1.in.applicationinsights.azure.com/;LiveEndpoint=https://australiaeast.livediagnostics.monitor.azure.com/;ApplicationId=8404bd9a-2eda-40de-a2d5-11015a59d55f",
      "resourceGroup": "of-8-6-cloud-rg",
      "location": "australiaeast",
      "provisioningState": "Succeeded"
    }
  },
  "configuration": {
    "retentionInDays": 90,
    "samplingEnabled": false,
    "ingestionMode": "LogAnalytics",
    "publicNetworkAccess": "Enabled"
  },
  "status": "completed"
}